{
  "display": {
    "icon": {
      "item": "doz_in_maincraft:case_shooting_range_3"
    },
    "title": {
      "translate": "advancements.what_are_you_up_to.title"
    },
    "description": {
      "translate": "advancements.what_are_you_up_to.descr"
    },
    "frame": "task",
    "show_toast": true,
    "announce_to_chat": true,
    "hidden": false
  },
  "criteria": {
    "what_are_you_up_to_0": {
      "trigger": "minecraft:inventory_changed",
      "conditions": {
        "items": [
          {
            "items": [
              "doz_in_maincraft:case_shooting_range_3"
            ],
            "count": {
              "min": 1,
              "max": 1
            }
          }
        ]
      }
    }
  },
  "parent": "doz_in_maincraft:well_why_dont_you_have_a_chest"
}