{
  "_fv": 73,
  "_type": "recipe",
  "definition": {
    "recipeType": "Crafting",
    "recipeRetstackSize": 1,
    "group": "",
    "cookingBookCategory": "MISC",
    "xpReward": 0.0,
    "cookingTime": 200,
    "craftingBookCategory": "MISC",
    "recipeShapeless": false,
    "recipeSlots": [
      {
        "value": ""
      },
      {
        "value": ""
      },
      {
        "value": "Items.EMERALD"
      },
      {
        "value": "CUSTOM:IronPlates"
      },
      {
        "value": "CUSTOM:IronPlates"
      },
      {
        "value": "Items.REDSTONE"
      },
      {
        "value": "Blocks.IRON_BLOCK"
      },
      {
        "value": ""
      },
      {
        "value": "Blocks.LOG"
      }
    ],
    "recipeReturnStack": {
      "value": "CUSTOM:ArmorersWorkbench"
    },
    "name": "iauu",
    "namespace": "mod"
  }
}