{
  "_fv": 73,
  "_type": "gui",
  "definition": {
    "type": 1,
    "width": 176,
    "height": 166,
    "inventoryOffsetX": 0,
    "inventoryOffsetY": 0,
    "renderBgLayer": true,
    "doesPauseGame": false,
    "components": [
      {
        "type": "outputslot",
        "data": {
          "id": 0,
          "disablePickup": {
            "fixedValue": false
          },
          "dropItemsWhenNotBound": true,
          "x": 159,
          "y": 53,
          "locked": false
        }
      },
      {
        "type": "outputslot",
        "data": {
          "id": 1,
          "disablePickup": {
            "fixedValue": false
          },
          "dropItemsWhenNotBound": true,
          "x": 177,
          "y": 53,
          "locked": false
        }
      },
      {
        "type": "outputslot",
        "data": {
          "id": 2,
          "disablePickup": {
            "fixedValue": false
          },
          "dropItemsWhenNotBound": true,
          "x": 195,
          "y": 53,
          "locked": false
        }
      },
      {
        "type": "outputslot",
        "data": {
          "id": 3,
          "disablePickup": {
            "fixedValue": false
          },
          "dropItemsWhenNotBound": true,
          "x": 213,
          "y": 53,
          "locked": false
        }
      },
      {
        "type": "outputslot",
        "data": {
          "id": 4,
          "disablePickup": {
            "fixedValue": false
          },
          "dropItemsWhenNotBound": true,
          "x": 231,
          "y": 53,
          "locked": false
        }
      },
      {
        "type": "outputslot",
        "data": {
          "id": 5,
          "disablePickup": {
            "fixedValue": false
          },
          "dropItemsWhenNotBound": true,
          "x": 249,
          "y": 53,
          "locked": false
        }
      },
      {
        "type": "outputslot",
        "data": {
          "id": 6,
          "disablePickup": {
            "fixedValue": false
          },
          "dropItemsWhenNotBound": true,
          "x": 159,
          "y": 71,
          "locked": false
        }
      },
      {
        "type": "outputslot",
        "data": {
          "id": 7,
          "disablePickup": {
            "fixedValue": false
          },
          "dropItemsWhenNotBound": true,
          "x": 177,
          "y": 71,
          "locked": false
        }
      },
      {
        "type": "outputslot",
        "data": {
          "id": 8,
          "disablePickup": {
            "fixedValue": false
          },
          "dropItemsWhenNotBound": true,
          "x": 195,
          "y": 71,
          "locked": false
        }
      },
      {
        "type": "outputslot",
        "data": {
          "id": 9,
          "disablePickup": {
            "fixedValue": false
          },
          "dropItemsWhenNotBound": true,
          "x": 213,
          "y": 71,
          "locked": false
        }
      },
      {
        "type": "outputslot",
        "data": {
          "id": 10,
          "disablePickup": {
            "fixedValue": false
          },
          "dropItemsWhenNotBound": true,
          "x": 231,
          "y": 71,
          "locked": false
        }
      },
      {
        "type": "outputslot",
        "data": {
          "id": 11,
          "disablePickup": {
            "fixedValue": false
          },
          "dropItemsWhenNotBound": true,
          "x": 249,
          "y": 71,
          "locked": false
        }
      }
    ],
    "gridSettings": {
      "sx": 18,
      "sy": 18,
      "ox": 11,
      "oy": 15,
      "snapOnGrid": true
    }
  }
}